{
  "project_info": {
    "project_number": "747795371497",
    "project_id": "forms-a1df9",
    "storage_bucket": "forms-a1df9.firebasestorage.app"
  },
  "client": [
    {
      "client_info": {
        "mobilesdk_app_id": "1:747795371497:android:ca85b3046958933f01e778",
        "android_client_info": {
          "package_name": "com.wakana.secureforms"
        }
      },
      "oauth_client": [],
      "api_key": [
        {
          "current_key": "AIzaSyAL8lhOYa6bY0sQ8WslVI5ROFi72sN8KbA"
        }
      ],
      "services": {
        "appinvite_service": {
          "other_platform_oauth_client": []
        }
      }
    }
  ],
  "configuration_version": "1"
}